snowplow_signals/__init__.py
snowplow_signals/api_client.py
snowplow_signals/attributes_client.py
snowplow_signals/batch_autogen/__init__.py
snowplow_signals/batch_autogen/cli.py
snowplow_signals/batch_autogen/cli_params.py
snowplow_signals/batch_autogen/dbt_client.py
snowplow_signals/batch_autogen/models/__init__.py
snowplow_signals/batch_autogen/models/allowed_atomic_properties.txt
snowplow_signals/batch_autogen/models/base_config_generator.py
snowplow_signals/batch_autogen/models/batch_source_config.py
snowplow_signals/batch_autogen/models/dbt_asset_generator.py
snowplow_signals/batch_autogen/models/dbt_config_generator.py
snowplow_signals/batch_autogen/models/dbt_project_setup.py
snowplow_signals/batch_autogen/models/model.py
snowplow_signals/batch_autogen/models/modeling_step.py
snowplow_signals/batch_autogen/schemas.py
snowplow_signals/batch_autogen/templates/allow_refresh.j2
snowplow_signals/batch_autogen/templates/attributes.j2
snowplow_signals/batch_autogen/templates/base_events_this_run.j2
snowplow_signals/batch_autogen/templates/base_new_event_limits.j2
snowplow_signals/batch_autogen/templates/daily_aggregates.j2
snowplow_signals/batch_autogen/templates/daily_aggregates_this_run.j2
snowplow_signals/batch_autogen/templates/daily_aggregation_manifest.j2
snowplow_signals/batch_autogen/templates/days_to_process.j2
snowplow_signals/batch_autogen/templates/dbt_project.j2
snowplow_signals/batch_autogen/templates/filtered_events.j2
snowplow_signals/batch_autogen/templates/filtered_events_this_run.j2
snowplow_signals/batch_autogen/templates/get_cluster_by_values.j2
snowplow_signals/batch_autogen/templates/get_limits_for_attributes.j2
snowplow_signals/batch_autogen/templates/incremental_manifest.j2
snowplow_signals/batch_autogen/templates/packages.j2
snowplow_signals/batch_autogen/templates/src_base.j2
snowplow_signals/batch_autogen/utils/__init__.py
snowplow_signals/batch_autogen/utils/utils.py
snowplow_signals/cli_logging.py
snowplow_signals/definitions.py
snowplow_signals-0.4.1.dist-info/METADATA
snowplow_signals-0.4.1.dist-info/WHEEL
snowplow_signals-0.4.1.dist-info/entry_points.txt
snowplow_signals-0.4.1.dist-info/licenses/LICENSE
snowplow_signals-0.4.1.dist-info/RECORD
