Metadata-Version: 2.4
Name: snowplow-signals
Version: 0.4.1
Summary: 
License-File: LICENSE
Author: Snowplow
Author-email: support@snowplow.io
Requires-Python: >=3.11,<4.0
Classifier: License :: OSI Approved :: Apache Software License
Classifier: Programming Language :: Python :: 3
Classifier: Programming Language :: Python :: 3.11
Classifier: Programming Language :: Python :: 3.12
Classifier: Programming Language :: Python :: 3.13
Classifier: Programming Language :: Python :: 3.14
Provides-Extra: batch-engine
Requires-Dist: httpx (>=0.28.1,<0.29.0)
Requires-Dist: jinja2 (>=3.1.6,<4.0.0) ; extra == "batch-engine"
Requires-Dist: jsonpath-ng (>=1.7.0,<2.0.0)
Requires-Dist: pandas (>=2.2.0,<3.0.0)
Requires-Dist: pydantic[email] (>=2.10.6,<3.0.0)
Requires-Dist: pyjwt (>=2.10.1,<3.0.0)
Requires-Dist: sqlglot (>=26.16.4,<27.0.0) ; extra == "batch-engine"
Requires-Dist: typer (>=0.15.2,<0.16.0) ; extra == "batch-engine"
